kute/__init__.py
kute/__main__.py
kute/_kute.py
kute/constants.py
kute/loaders.py
kute/analysis/__init__.py
kute/analysis/_com_velocity.py
kute/analysis/_electric_current.py
kute/analysis/_kuteanalysis.py
kute/analysis/_pressure_tensor.py
kute/reporters/__init__.py
kute/reporters/_comvelocityreporter.py
kute/reporters/_electriccurrentreporter.py
kute/reporters/_pressuretensorreporter.py
kute/reporters/_spatialelectriccurrentreporter.py
kute/routines/_ascii_logo.py
kute/routines/_calculate_microscopic_current.py
kute/routines/_calculate_transport_coefficient.py
kute/routines/_join_currents.py
kute-1.3.4.dist-info/licenses/LICENSE
kute-1.3.4.dist-info/METADATA
kute-1.3.4.dist-info/WHEEL
kute-1.3.4.dist-info/entry_points.txt
kute-1.3.4.dist-info/top_level.txt
kute-1.3.4.dist-info/RECORD
