Metadata-Version: 2.4
Name: kute
Version: 1.3.4
Summary: green Kubo Uncertainty-based Transport Estimator
Author-email: Martín Otero-Lema <martin.oterolema@usc.es>, Raúl Lois-Cuns <raul.lois.cuns@usc.es>
Classifier: Programming Language :: Python :: 3
Classifier: License :: OSI Approved :: MIT License
Classifier: Operating System :: OS Independent
License-File: LICENSE
Requires-Dist: MDAnalysis
Requires-Dist: numpy
Requires-Dist: scipy
Requires-Dist: h5py
Requires-Dist: packaging
Requires-Dist: pytest
Provides-Extra: reporters
Requires-Dist: Openmm; extra == "reporters"
Provides-Extra: analysis
Requires-Dist: dask; extra == "analysis"
Dynamic: license-file
